llmate/__init__.py
llmate/cli.py
quick_question-0.1.0.dist-info/LICENSE
quick_question-0.1.0.dist-info/METADATA
quick_question-0.1.0.dist-info/WHEEL
quick_question-0.1.0.dist-info/entry_points.txt
quick_question-0.1.0.dist-info/top_level.txt
quick_question-0.1.0.dist-info/RECORD
